liath/__init__.py
liath/cli.py
liath/cli_entry.py
liath/database.py
liath/embedded.py
liath/example/basic_perplexity.lua
liath/luarocks/bin/json2lua
liath/luarocks/bin/lua2json
liath/luarocks/share/lua/5.4/cjson/util.lua
liath/luarocks/share/lua/5.4/htmlEntities.lua
liath/luarocks/share/lua/5.4/json2lua.lua
liath/luarocks/share/lua/5.4/ltn12.lua
liath/luarocks/share/lua/5.4/lua2json.lua
liath/luarocks/share/lua/5.4/lyaml/explicit.lua
liath/luarocks/share/lua/5.4/lyaml/functional.lua
liath/luarocks/share/lua/5.4/lyaml/implicit.lua
liath/luarocks/share/lua/5.4/lyaml/init.lua
liath/luarocks/share/lua/5.4/markdown.lua
liath/luarocks/share/lua/5.4/mime.lua
liath/luarocks/share/lua/5.4/socket/ftp.lua
liath/luarocks/share/lua/5.4/socket/headers.lua
liath/luarocks/share/lua/5.4/socket/http.lua
liath/luarocks/share/lua/5.4/socket/smtp.lua
liath/luarocks/share/lua/5.4/socket/tp.lua
liath/luarocks/share/lua/5.4/socket/url.lua
liath/luarocks/share/lua/5.4/socket.lua
liath/luarocks/share/lua/5.4/ssl/https.lua
liath/luarocks/share/lua/5.4/ssl.lua
liath/plugin_base.py
liath/plugins/backup_restore_plugin.py
liath/plugins/db_plugin.py
liath/plugins/embed_plugin.py
liath/plugins/file_plugin.py
liath/plugins/llm_plugin.py
liath/plugins/monitoring_logging_plugin.py
liath/plugins/query_cache_plugin.py
liath/plugins/vdb_plugin.py
liath/server.py
liath/setup_luarocks.sh
liath/storage/base.py
liath/storage/leveldb_storage.py
liath/storage/rocksdb_storage.py
liath/test_data/auth.db/LOCK
liath/test_data/auth.db/LOG
liath/test_data/auth.db/LOG.old
liath/test_database.py
liath-0.1.0.dist-info/LICENSE
liath-0.1.0.dist-info/METADATA
liath-0.1.0.dist-info/WHEEL
liath-0.1.0.dist-info/entry_points.txt
liath-0.1.0.dist-info/RECORD
