Metadata-Version: 2.3
Name: liath
Version: 0.1.0
Summary: An AI-powered database system with key-value storage, vector search, and AI capabilities
License: MIT
Keywords: database,ai,llm,key-value,lua,vector-search
Author: Dipankar Sarkar
Author-email: me@dipankar.name
Requires-Python: >=3.11,<3.13
Classifier: Development Status :: 3 - Alpha
Classifier: Intended Audience :: Developers
Classifier: License :: OSI Approved :: MIT License
Classifier: Programming Language :: Python :: 3
Classifier: Programming Language :: Python :: 3.11
Classifier: Programming Language :: Python :: 3.12
Classifier: Topic :: Database
Classifier: Topic :: Database :: Database Engines/Servers
Classifier: Topic :: Scientific/Engineering :: Artificial Intelligence
Provides-Extra: rocksdb
Requires-Dist: fastembed (>=0.3.4,<0.4.0)
Requires-Dist: flask-smorest (>=0.44.0,<0.45.0)
Requires-Dist: llama-cpp-python (>=0.2.85,<0.3.0)
Requires-Dist: lupa (>=2.5,<3.0)
Requires-Dist: openai (>=1.40.0,<2.0.0)
Requires-Dist: pandas (>=2.2.2,<3.0.0)
Requires-Dist: plyvel (>=1.5.1,<2.0.0)
Requires-Dist: psutil (>=6.0.0,<7.0.0)
Requires-Dist: pytest (>=8.4.1,<9.0.0)
Requires-Dist: pyyaml (>=6.0.1,<7.0.0)
Requires-Dist: usearch (>=2.13.0,<3.0.0)
Project-URL: Repository, https://github.com/skelf-research/liath
